gdextension_cli/__init__.py
gdextension_cli/__version__.py
gdextension_cli/command_line_args.py
gdextension_cli/git.py
gdextension_cli/template_renderer.py
gdextension_cli/commands/new_project_from_git.py
gdextension_cli/commands/new_project_from_local.py
gdextension_cli-0.0.4.dist-info/METADATA
gdextension_cli-0.0.4.dist-info/WHEEL
gdextension_cli-0.0.4.dist-info/entry_points.txt
gdextension_cli-0.0.4.dist-info/licenses/LICENSE
gdextension_cli-0.0.4.dist-info/RECORD
