Metadata-Version: 2.3
Name: gdextension-cli
Version: 0.0.4
Summary: A command line interface for Godot's GDExtension
Project-URL: Homepage, https://github.com/3LK3/gdextension-cli
Project-URL: Bug Tracker, https://github.com/3LK3/gdextension-cli/issues
Author-email: Sören Spindler <soeren.s89@gmail.com>
License-File: LICENSE
Classifier: Programming Language :: Python :: 3
Requires-Python: >=3.8
Requires-Dist: jinja2==3.1.4
